CHANGELOG.rst
LICENSE.txt
MANIFEST.in
README.rst
TODO.rst
VERSION.txt
notes.txt
process-barleymon.txt
process-rpi3.txt
process.txt
setup.cfg
setup.py
raspi_door/__init__.py
raspi_door/alert.py
raspi_door/app.py
raspi_door/button.py
raspi_door/camera.py
raspi_door/cli.py
raspi_door/clock.py
raspi_door/event.py
raspi_door/i18n.py
raspi_door/icon.py
raspi_door/label.py
raspi_door/lock.py
raspi_door/sensor.py
raspi_door/service.py
raspi_door/sizer.py
raspi_door/trap.py
raspi_door/ui.py
raspi_door/util.py
raspi_door/weather.py
raspi_door.egg-info/PKG-INFO
raspi_door.egg-info/SOURCES.txt
raspi_door.egg-info/dependency_links.txt
raspi_door.egg-info/entry_points.txt
raspi_door.egg-info/not-zip-safe
raspi_door.egg-info/requires.txt
raspi_door.egg-info/top_level.txt
raspi_door/plugins/__init__.py
raspi_door/plugins/weather/__init__.py
raspi_door/plugins/weather/openweathermap.py
raspi_door/plugins/weather/yahoo.py
raspi_door/res/config.ini
raspi_door/res/wx.en.xrc
raspi_door/res/yahoo-weather-conditions-svg.css
raspi_door/res/audio/doorbell.ogg
raspi_door/res/audio/readytoserve.ogg
raspi_door/res/image/camera-na.png
raspi_door/res/image/icon-action-cam.png
raspi_door/res/image/icon-action-exit.png
raspi_door/res/image/icon-action-info.png
raspi_door/res/image/icon-action-lock.png
raspi_door/res/image/icon-action-message.png
raspi_door/res/image/icon-action-permlock.png
raspi_door/res/image/icon-action-unlock.png
raspi_door/res/image/weather-cold.png
raspi_door/res/image/weather-hot.png
raspi_door/res/image/weather-na.png
raspi_door/res/image/yahoo-blowing-snow.png
raspi_door/res/image/yahoo-blustery.png
raspi_door/res/image/yahoo-clear-d.png
raspi_door/res/image/yahoo-clear-n.png
raspi_door/res/image/yahoo-cloudy.png
raspi_door/res/image/yahoo-cold.png
raspi_door/res/image/yahoo-default.png
raspi_door/res/image/yahoo-drizzle.png
raspi_door/res/image/yahoo-dust.png
raspi_door/res/image/yahoo-fair-d.png
raspi_door/res/image/yahoo-fair-n.png
raspi_door/res/image/yahoo-foggy.png
raspi_door/res/image/yahoo-freezing-drizzle.png
raspi_door/res/image/yahoo-freezing-rain.png
raspi_door/res/image/yahoo-hail.png
raspi_door/res/image/yahoo-haze.png
raspi_door/res/image/yahoo-heavy-snow.png
