Metadata-Version: 1.1
Name: raspi-door
Version: 0.7.1
Summary: Raspberry Pi Smart-ish Door
Home-page: http://github.com/metagriffin/raspi-door
Author: metagriffin
Author-email: mg.pypi@metagriffin.net
License: GPLv3+
Keywords: raspberry pi door smart-ish automation recognition gui
Platform: any
Classifier: Development Status :: 2 - Pre-Alpha
Classifier: Environment :: X11 Applications
Classifier: Environment :: Win32 (MS Windows)
Classifier: Environment :: MacOS X
Classifier: Environment :: Other Environment
Classifier: Natural Language :: English
Classifier: Operating System :: OS Independent
Classifier: Programming Language :: Python
Classifier: Intended Audience :: End Users/Desktop
Classifier: Topic :: Home Automation
Classifier: Topic :: Utilities
Classifier: Topic :: Security
Classifier: Topic :: Multimedia :: Video :: Capture
Classifier: Topic :: Scientific/Engineering :: Image Recognition
Classifier: License :: OSI Approved :: GNU General Public License v3 or later (GPLv3+)
